{"name":"Verify a successful registration in Utest","id":"i-as-a-utest-user;verify-a-successful-registration-in-utest","testSteps":[{"number":1,"description":"Given than user enters the website","duration":7497,"startTime":"2022-04-13T14:10:25.104-05:00[America/Bogota]","screenshots":[{"screenshot":"cda1a66da316d0ac6904ad26b77239c964ce96d83d2404ceddb10e0f0a19d805.png"}],"result":"SUCCESS","precondition":false,"children":[{"number":2,"description":"user opens the Utest home page","duration":7053,"startTime":"2022-04-13T14:10:25.387-05:00[America/Bogota]","screenshots":[{"screenshot":"cda1a66da316d0ac6904ad26b77239c964ce96d83d2404ceddb10e0f0a19d805.png"}],"result":"SUCCESS","precondition":false}]},{"number":3,"description":"When you fill out the registration form\r\n| strFirstName | strLastName | strEmail |\r\n| luis | Perez | pepitoperez@ramau.com |","duration":8482,"startTime":"2022-04-13T14:10:32.602-05:00[America/Bogota]","exception":{"errorType":"org.openqa.selenium.ElementNotInteractableException","message":"The following error occurred: element not interactable\n  (Session info: chrome\u003d100.0.4896.88)\nBuild info: version: \u00273.11.0\u0027, revision: \u0027e59cfb3\u0027, time: \u00272018-03-11T20:26:55.152Z\u0027\nSystem info: host: \u0027CHMEPPF350WY6\u0027, ip: \u0027192.168.1.35\u0027, os.name: \u0027Windows 10\u0027, os.arch: \u0027amd64\u0027, os.version: \u002710.0\u0027, java.version: \u00271.8.0_131\u0027\nDriver info: org.openqa.selenium.remote.RemoteWebDriver\nCapabilities {acceptInsecureCerts: false, browserName: chrome, browserVersion: 100.0.4896.88, chrome: {chromedriverVersion: 100.0.4896.20 (f9d71f93d32a..., userDataDir: C:\\Users\\lpetro\\AppData\\Loc...}, goog:chromeOptions: {debuggerAddress: localhost:58739}, javascriptEnabled: true, networkConnectionEnabled: false, pageLoadStrategy: normal, platform: WINDOWS, platformName: WINDOWS, proxy: Proxy(), setWindowRect: true, strictFileInteractability: false, timeouts: {implicit: 0, pageLoad: 300000, script: 30000}, unhandledPromptBehavior: dismiss and notify, webauthn:extension:credBlob: true, webauthn:extension:largeBlob: true, webauthn:virtualAuthenticators: true}\nSession ID: 46cd7424d22549c7e245150a80ecb95e","stackTrace":[{"declaringClass":"pruebautes.tasks.FillForm","methodName":"performAs","fileName":"FillForm.java","lineNumber":31},{"declaringClass":"pruebautes.stepdefinitions.UtestStepDefinitions","methodName":"youFillOutTheRegistrationForm","fileName":"UtestStepDefinitions.java","lineNumber":30},{"declaringClass":"cucumber.runner.Runner","methodName":"runPickle","fileName":"Runner.java","lineNumber":80}]},"result":"ERROR","precondition":false,"children":[{"number":4,"description":"user clicks on Button join today","duration":278,"startTime":"2022-04-13T14:10:32.659-05:00[America/Bogota]","screenshots":[{"screenshot":"ca8815f8013ab04d36871fd4dc485ec9b02a229c8c42f222e31a29611b2c2e6b.png"}],"result":"SUCCESS","precondition":false},{"number":5,"description":"user enters \u0027luis\u0027 into First Name","duration":714,"startTime":"2022-04-13T14:10:32.939-05:00[America/Bogota]","screenshots":[{"screenshot":"decd9b3685814ed56cfcc8ebe97664bb518b08129cf969c49504461ca39abf2a.png"}],"result":"SUCCESS","precondition":false},{"number":6,"description":"user enters \u0027Perez\u0027 into Register lastname user","duration":407,"startTime":"2022-04-13T14:10:33.655-05:00[America/Bogota]","screenshots":[{"screenshot":"7224fbfcdeea709d97c05a7aab603a47ffba2ee9ba61b6c7c84ff91c1839d4f5.png"}],"result":"SUCCESS","precondition":false},{"number":7,"description":"user enters \u0027pepitoperez@ramau.com\u0027 into Register lastname user","duration":397,"startTime":"2022-04-13T14:10:34.063-05:00[America/Bogota]","screenshots":[{"screenshot":"5d1a6429eec522f77ef2ed49c2431c847337de18a7cb224d3a336f9c19b1ac56.png"}],"result":"SUCCESS","precondition":false},{"number":8,"description":"user select October on Last Name","duration":406,"startTime":"2022-04-13T14:10:34.461-05:00[America/Bogota]","screenshots":[{"screenshot":"f71032edbc435253cbd17d6a3c76b0978cb184dfab967d7f79133fd7aab9408a.png"}],"result":"SUCCESS","precondition":false},{"number":9,"description":"user select 15 on Last Name","duration":436,"startTime":"2022-04-13T14:10:34.871-05:00[America/Bogota]","screenshots":[{"screenshot":"b037873de004892e7d314ba692cfae301310932816aca7866fc131982c06e190.png"}],"result":"SUCCESS","precondition":false},{"number":10,"description":"user select 1994 on Last Name","duration":942,"startTime":"2022-04-13T14:10:35.309-05:00[America/Bogota]","screenshots":[{"screenshot":"6f09c31d2842943a3b3190e2a94714ecdea38ced71bf3a7f57a3e933ca3133c8.png"}],"result":"SUCCESS","precondition":false},{"number":11,"description":"user clicks on apartado simular","duration":550,"startTime":"2022-04-13T14:10:36.253-05:00[America/Bogota]","screenshots":[{"screenshot":"39bddca89488cbf51d4ea6b8f5442ae9dd5bda0ec1af677efcb346f3ceac5e3c.png"}],"result":"SUCCESS","precondition":false},{"number":12,"description":"user enters \u0027Montería\u0027 into Last Name","duration":571,"startTime":"2022-04-13T14:10:36.805-05:00[America/Bogota]","screenshots":[{"screenshot":"cab1fb851e74abfdb393216ff352be922c8a823d99052b9f0079bf6b9b886960.png"}],"result":"SUCCESS","precondition":false},{"number":13,"description":"user types \u0027ARROW_DOWN\u0027 in Last Name","duration":377,"startTime":"2022-04-13T14:10:37.378-05:00[America/Bogota]","screenshots":[{"screenshot":"e883135153fb7cf6cd75355c4df7ada7dcee0f3495116d990eb76e9b2cbab1d7.png"}],"result":"SUCCESS","precondition":false},{"number":14,"description":"user enters \u002750345\u0027 into apartado simular","duration":441,"startTime":"2022-04-13T14:10:37.757-05:00[America/Bogota]","screenshots":[{"screenshot":"804236a3030a4ebf145678287cb1b67a3b75c0e72c106fa5093e78c91b89dead.png"}],"result":"SUCCESS","precondition":false},{"number":15,"description":"user types \u0027ARROW_DOWN\u0027 in apartado simular","duration":308,"startTime":"2022-04-13T14:10:38.200-05:00[America/Bogota]","screenshots":[{"screenshot":"2777eb124aec380fe9389a2611a1b1a7e2ca591a810c17f41ca4656bbab0ca42.png"}],"result":"SUCCESS","precondition":false},{"number":16,"description":"user enters \u0027Venezuela\u0027 into apartado simular","duration":2572,"startTime":"2022-04-13T14:10:38.510-05:00[America/Bogota]","screenshots":[{"screenshot":"aceb8943d7fcb30d53cc08f504b25b85417a10b934fc45988e7be01a23022c8f.png","htmlSource":"pagesource2484742066786863904.html.txt"}],"exception":{"errorType":"org.openqa.selenium.ElementNotInteractableException","message":"The following error occurred: element not interactable\n  (Session info: chrome\u003d100.0.4896.88)\nBuild info: version: \u00273.11.0\u0027, revision: \u0027e59cfb3\u0027, time: \u00272018-03-11T20:26:55.152Z\u0027\nSystem info: host: \u0027CHMEPPF350WY6\u0027, ip: \u0027192.168.1.35\u0027, os.name: \u0027Windows 10\u0027, os.arch: \u0027amd64\u0027, os.version: \u002710.0\u0027, java.version: \u00271.8.0_131\u0027\nDriver info: org.openqa.selenium.remote.RemoteWebDriver\nCapabilities {acceptInsecureCerts: false, browserName: chrome, browserVersion: 100.0.4896.88, chrome: {chromedriverVersion: 100.0.4896.20 (f9d71f93d32a..., userDataDir: C:\\Users\\lpetro\\AppData\\Loc...}, goog:chromeOptions: {debuggerAddress: localhost:58739}, javascriptEnabled: true, networkConnectionEnabled: false, pageLoadStrategy: normal, platform: WINDOWS, platformName: WINDOWS, proxy: Proxy(), setWindowRect: true, strictFileInteractability: false, timeouts: {implicit: 0, pageLoad: 300000, script: 30000}, unhandledPromptBehavior: dismiss and notify, webauthn:extension:credBlob: true, webauthn:extension:largeBlob: true, webauthn:virtualAuthenticators: true}\nSession ID: 46cd7424d22549c7e245150a80ecb95e","stackTrace":[{"declaringClass":"pruebautes.tasks.FillForm","methodName":"performAs","fileName":"FillForm.java","lineNumber":31},{"declaringClass":"pruebautes.stepdefinitions.UtestStepDefinitions","methodName":"youFillOutTheRegistrationForm","fileName":"UtestStepDefinitions.java","lineNumber":30},{"declaringClass":"cucumber.runner.Runner","methodName":"runPickle","fileName":"Runner.java","lineNumber":80}]},"result":"ERROR","precondition":false}]},{"number":17,"description":"Perform as: user","duration":4,"startTime":"2022-04-13T14:10:41.085-05:00[America/Bogota]","exception":{"errorType":"org.openqa.selenium.ElementNotInteractableException","message":"The following error occurred: element not interactable\n  (Session info: chrome\u003d100.0.4896.88)\nBuild info: version: \u00273.11.0\u0027, revision: \u0027e59cfb3\u0027, time: \u00272018-03-11T20:26:55.152Z\u0027\nSystem info: host: \u0027CHMEPPF350WY6\u0027, ip: \u0027192.168.1.35\u0027, os.name: \u0027Windows 10\u0027, os.arch: \u0027amd64\u0027, os.version: \u002710.0\u0027, java.version: \u00271.8.0_131\u0027\nDriver info: org.openqa.selenium.remote.RemoteWebDriver\nCapabilities {acceptInsecureCerts: false, browserName: chrome, browserVersion: 100.0.4896.88, chrome: {chromedriverVersion: 100.0.4896.20 (f9d71f93d32a..., userDataDir: C:\\Users\\lpetro\\AppData\\Loc...}, goog:chromeOptions: {debuggerAddress: localhost:58739}, javascriptEnabled: true, networkConnectionEnabled: false, pageLoadStrategy: normal, platform: WINDOWS, platformName: WINDOWS, proxy: Proxy(), setWindowRect: true, strictFileInteractability: false, timeouts: {implicit: 0, pageLoad: 300000, script: 30000}, unhandledPromptBehavior: dismiss and notify, webauthn:extension:credBlob: true, webauthn:extension:largeBlob: true, webauthn:virtualAuthenticators: true}\nSession ID: 46cd7424d22549c7e245150a80ecb95e","stackTrace":[{"declaringClass":"pruebautes.tasks.FillForm","methodName":"performAs","fileName":"FillForm.java","lineNumber":31},{"declaringClass":"pruebautes.stepdefinitions.UtestStepDefinitions","methodName":"youFillOutTheRegistrationForm","fileName":"UtestStepDefinitions.java","lineNumber":30},{"declaringClass":"cucumber.runner.Runner","methodName":"runPickle","fileName":"Runner.java","lineNumber":80}]},"result":"ERROR","precondition":false}],"userStory":{"id":"i-as-a-utest-user","storyName":"I as a Utest user","path":"src/test/resources/features/Utest.feature","narrative":"  I want to be able to register on your website\n  To have access to all its functions","type":"feature"},"featureTag":{"name":"Features/I as a Utest user","type":"feature"},"title":"Verify a successful registration in Utest","tags":[{"name":"I as a utest user","type":"feature"},{"name":"stories","type":"tag"}],"startTime":"2022-04-13T14:10:24.733-05:00[America/Bogota]","duration":16604,"testFailureCause":{"errorType":"org.openqa.selenium.ElementNotInteractableException","message":"The following error occurred: element not interactable\n  (Session info: chrome\u003d100.0.4896.88)\nBuild info: version: \u00273.11.0\u0027, revision: \u0027e59cfb3\u0027, time: \u00272018-03-11T20:26:55.152Z\u0027\nSystem info: host: \u0027CHMEPPF350WY6\u0027, ip: \u0027192.168.1.35\u0027, os.name: \u0027Windows 10\u0027, os.arch: \u0027amd64\u0027, os.version: \u002710.0\u0027, java.version: \u00271.8.0_131\u0027\nDriver info: org.openqa.selenium.remote.RemoteWebDriver\nCapabilities {acceptInsecureCerts: false, browserName: chrome, browserVersion: 100.0.4896.88, chrome: {chromedriverVersion: 100.0.4896.20 (f9d71f93d32a..., userDataDir: C:\\Users\\lpetro\\AppData\\Loc...}, goog:chromeOptions: {debuggerAddress: localhost:58739}, javascriptEnabled: true, networkConnectionEnabled: false, pageLoadStrategy: normal, platform: WINDOWS, platformName: WINDOWS, proxy: Proxy(), setWindowRect: true, strictFileInteractability: false, timeouts: {implicit: 0, pageLoad: 300000, script: 30000}, unhandledPromptBehavior: dismiss and notify, webauthn:extension:credBlob: true, webauthn:extension:largeBlob: true, webauthn:virtualAuthenticators: true}\nSession ID: 46cd7424d22549c7e245150a80ecb95e","stackTrace":[{"declaringClass":"pruebautes.tasks.FillForm","methodName":"performAs","fileName":"FillForm.java","lineNumber":31},{"declaringClass":"pruebautes.stepdefinitions.UtestStepDefinitions","methodName":"youFillOutTheRegistrationForm","fileName":"UtestStepDefinitions.java","lineNumber":30},{"declaringClass":"cucumber.runner.Runner","methodName":"runPickle","fileName":"Runner.java","lineNumber":80}]},"testFailureClassname":"org.openqa.selenium.ElementNotInteractableException","testFailureMessage":"The following error occurred: element not interactable\n  (Session info: chrome\u003d100.0.4896.88)\nBuild info: version: \u00273.11.0\u0027, revision: \u0027e59cfb3\u0027, time: \u00272018-03-11T20:26:55.152Z\u0027\nSystem info: host: \u0027CHMEPPF350WY6\u0027, ip: \u0027192.168.1.35\u0027, os.name: \u0027Windows 10\u0027, os.arch: \u0027amd64\u0027, os.version: \u002710.0\u0027, java.version: \u00271.8.0_131\u0027\nDriver info: org.openqa.selenium.remote.RemoteWebDriver\nCapabilities {acceptInsecureCerts: false, browserName: chrome, browserVersion: 100.0.4896.88, chrome: {chromedriverVersion: 100.0.4896.20 (f9d71f93d32a..., userDataDir: C:\\Users\\lpetro\\AppData\\Loc...}, goog:chromeOptions: {debuggerAddress: localhost:58739}, javascriptEnabled: true, networkConnectionEnabled: false, pageLoadStrategy: normal, platform: WINDOWS, platformName: WINDOWS, proxy: Proxy(), setWindowRect: true, strictFileInteractability: false, timeouts: {implicit: 0, pageLoad: 300000, script: 30000}, unhandledPromptBehavior: dismiss and notify, webauthn:extension:credBlob: true, webauthn:extension:largeBlob: true, webauthn:virtualAuthenticators: true}\nSession ID: 46cd7424d22549c7e245150a80ecb95e","testFailureSummary":"ERROR;org.openqa.selenium.ElementNotInteractableException;The following error occurred: element not interactable\n  (Session info: chrome\u003d100.0.4896.88)\nBuild info: version: \u00273.11.0\u0027, revision: \u0027e59cfb3\u0027, time: \u00272018-03-11T20:26:55.152Z\u0027\nSystem info: host: \u0027CHMEPPF350WY6\u0027, ip: \u0027192.168.1.35\u0027, os.name: \u0027Windows 10\u0027, os.arch: \u0027amd64\u0027, os.version: \u002710.0\u0027, java.version: \u00271.8.0_131\u0027\nDriver info: org.openqa.selenium.remote.RemoteWebDriver\nCapabilities {acceptInsecureCerts: false, browserName: chrome, browserVersion: 100.0.4896.88, chrome: {chromedriverVersion: 100.0.4896.20 (f9d71f93d32a..., userDataDir: C:\\Users\\lpetro\\AppData\\Loc...}, goog:chromeOptions: {debuggerAddress: localhost:58739}, javascriptEnabled: true, networkConnectionEnabled: false, pageLoadStrategy: normal, platform: WINDOWS, platformName: WINDOWS, proxy: Proxy(), setWindowRect: true, strictFileInteractability: false, timeouts: {implicit: 0, pageLoad: 300000, script: 30000}, unhandledPromptBehavior: dismiss and notify, webauthn:extension:credBlob: true, webauthn:extension:largeBlob: true, webauthn:virtualAuthenticators: true}\nSession ID: 46cd7424d22549c7e245150a80ecb95e;FillForm.java","projectKey":"","annotatedResult":"ERROR","sessionId":"46cd7424d22549c7e245150a80ecb95e","driver":"chrome:user","manual":false,"testSource":"Cucumber","result":"ERROR"}